process_tests.py
process_tests-3.0.0.dist-info/AUTHORS.rst
process_tests-3.0.0.dist-info/LICENSE
process_tests-3.0.0.dist-info/METADATA
process_tests-3.0.0.dist-info/WHEEL
process_tests-3.0.0.dist-info/top_level.txt
process_tests-3.0.0.dist-info/RECORD
